profitspace/__init__.py
profitspace/dataset.py
profitspace/space.py
profitspace/utils.py
trade_profit_space-0.1.0.dist-info/LICENSE
trade_profit_space-0.1.0.dist-info/METADATA
trade_profit_space-0.1.0.dist-info/WHEEL
trade_profit_space-0.1.0.dist-info/top_level.txt
trade_profit_space-0.1.0.dist-info/RECORD
