Metadata-Version: 2.1
Name: trade-profit-space
Version: 0.1.0
Summary: profitspace: is a Python package to map trade outcomes into a 2D profit space using OHLC data. Predict win, loss, expiration, and uncertainty of trades without relying on time.
Home-page: https://github.com/mehranESB/trade-profit-space.git
Author: Mehran ESMAILYBAJEGANI
Author-email: mehranesmaily907@gmail.com
License: MIT
Keywords: profitspace,finance,trading,machine learning,deep learning,OHLCV,technical analysis,deeptrading
Classifier: Development Status :: 3 - Alpha
Classifier: Intended Audience :: Developers
Classifier: Intended Audience :: Science/Research
Classifier: Topic :: Scientific/Engineering :: Artificial Intelligence
Classifier: Topic :: Software Development :: Libraries :: Python Modules
Classifier: Topic :: Office/Business :: Financial
Classifier: Topic :: Utilities
Classifier: License :: OSI Approved :: MIT License
Classifier: Programming Language :: Python :: 3
Classifier: Programming Language :: Python :: 3.8
Classifier: Programming Language :: Python :: 3.9
Classifier: Programming Language :: Python :: 3.10
Requires-Python: >=3.8
License-File: LICENSE
Requires-Dist: pandas
Requires-Dist: numpy
Requires-Dist: matplotlib
Requires-Dist: shapely
Requires-Dist: tqdm
